pyproject_external/__init__.py
pyproject_external/__main__.py
pyproject_external/_config.py
pyproject_external/_constants.py
pyproject_external/_exceptions.py
pyproject_external/_external.py
pyproject_external/_registry.py
pyproject_external/_sdist.py
pyproject_external/_system.py
pyproject_external/_url.py
pyproject_external/_version.py
pyproject_external/py.typed
pyproject_external/_cli/__init__.py
pyproject_external/_cli/_utils.py
pyproject_external/_cli/app.py
pyproject_external/_cli/build.py
pyproject_external/_cli/install.py
pyproject_external/_cli/prepare.py
pyproject_external/_cli/query.py
pyproject_external/_cli/show.py
pyproject_external-0.1.14.dist-info/METADATA
pyproject_external-0.1.14.dist-info/WHEEL
pyproject_external-0.1.14.dist-info/licenses/LICENSE
pyproject_external-0.1.14.dist-info/RECORD
