Metadata-Version: 2.4
Name: pyproject-external
Version: 0.1.14
Summary: Utilities to work with PEP 725 `[external]` metadata
Project-URL: homepage, https://github.com/jaimergp/pyproject-external
Author-email: Ralf Gommers <rgommers@quansight.com>, Jaime Rodríguez-Guerra <jrodriguez@quansight.com>
License: Copyright © 2023 Quansight Labs
License-File: LICENSE
Classifier: License :: OSI Approved :: MIT License
Classifier: Programming Language :: Python :: 3
Classifier: Programming Language :: Python :: 3 :: Only
Classifier: Programming Language :: Python :: 3.10
Classifier: Programming Language :: Python :: 3.11
Classifier: Programming Language :: Python :: 3.12
Classifier: Programming Language :: Python :: 3.13
Classifier: Programming Language :: Python :: Implementation :: CPython
Classifier: Programming Language :: Python :: Implementation :: PyPy
Requires-Python: >=3.10
Requires-Dist: build<2,>=1.4.0
Requires-Dist: click<9,>=8.3.1
Requires-Dist: dependency-groups<2,>=1.3.1
Requires-Dist: distro<2,>=1.9.0
Requires-Dist: jsonschema<5,>=4.26.0
Requires-Dist: packageurl-python<0.18,>=0.17.6
Requires-Dist: packaging<26,>=25.0
Requires-Dist: pip<26,>=25.3
Requires-Dist: platformdirs<5,>=4.5.1
Requires-Dist: pypi-json<0.5,>=0.4.0
Requires-Dist: requests<3,>=2.32.5
Requires-Dist: rich<15,>=14.2.0
Requires-Dist: tomli-w<2,>=1.2.0
Requires-Dist: tomli; python_full_version < '3.11'
Requires-Dist: typer<0.22,>=0.21.1
Requires-Dist: typing-extensions<5,>=4.15.0; python_full_version < '3.11'
